Metadata-Version: 2.1
Name: drawio-network-plot
Version: 0.0.02.Beta
Summary: Plot Network using python , and output to DrawIO file
Author: Amr ElHusseiny
Author-email: amroashram@hotmail.com
Keywords: python,first package
Classifier: Development Status :: 4 - Beta
Classifier: Topic :: System :: Networking
Requires-Python: >=3.6
License-File: LICENSE
